Metadata-Version: 1.1
Name: douyinti
Version: 0.1
Summary: add douyin effect to text
Home-page: https://github.com/pythonml/douyinti
Author: Zhongqiang Shen
Author-email: shenzhongqiang@msn.com
License: UNKNOWN
Platform: UNKNOWN
Classifier: Programming Language :: Python :: 3
Classifier: License :: OSI Approved :: MIT License
Classifier: Operating System :: OS Independent
